<batchelor>
    <!--plugin path="/opt/batchelor/plugin/execute.so"/-->
    <!--plugin path="/opt/batchelor/plugin/kubectl.so"/-->
    
    <connection>
        <setting key="url" value="http://127.0.0.1:8080"/>
        <setting key="username" value="product-id"/>
        <setting key="password" value="secret"/>
    </connection>
    
    <!--connection>
        <setting key="url" value="https://127.0.0.1:8080"/>
        <setting key="identity-provider" value="https://127.0.0.1:8080"/>
        <setting key="client-secret" value="product-secret"/>
    </connection-->
    
    <metric key="OS" value="Linux"/>
    <metric key="CPU_ARCH" value="x86_64"/>
    <metric key="CLOUD_ID" value="OnPrem"/>
</batchelor>
